apns_worker/__init__.py
apns_worker/apns.py
apns_worker/data.py
apns_worker/datetime.py
apns_worker/queue.py
apns_worker/backend/__init__.py
apns_worker/backend/base.py
apns_worker/backend/threaded.py
apns_worker/certs/anchors.pem
apns_worker/tests/__init__.py
apns_worker/tests/test_feedback.py
apns_worker/tests/test_message.py
apns_worker/tests/test_queue.py
apns_worker/tests/test_threaded_backend.py
apns_worker-0.1.dist-info/DESCRIPTION.rst
apns_worker-0.1.dist-info/METADATA
apns_worker-0.1.dist-info/metadata.json
apns_worker-0.1.dist-info/pbr.json
apns_worker-0.1.dist-info/RECORD
apns_worker-0.1.dist-info/top_level.txt
apns_worker-0.1.dist-info/WHEEL
