Metadata-Version: 2.0
Name: apns-worker
Version: 0.1
Summary: A robust client library for Apple's push notification service.
Home-page: https://github.com/bbits/apns-worker
Author: Peter Sagerson
Author-email: psagers@getcloak.com
License: BSD
Platform: UNKNOWN
Classifier: Development Status :: 4 - Beta
Classifier: Intended Audience :: Developers
Classifier: License :: OSI Approved :: BSD License
Classifier: Programming Language :: Python :: 2
Classifier: Programming Language :: Python :: 2.7
Classifier: Programming Language :: Python :: 3
Classifier: Programming Language :: Python :: 3.3
Classifier: Programming Language :: Python :: 3.4
Classifier: Programming Language :: Python :: 3.5
Requires-Dist: six
